easy_oidc_flow/__init__.py
easy_oidc_flow-1.0.1.dist-info/METADATA
easy_oidc_flow-1.0.1.dist-info/WHEEL
easy_oidc_flow-1.0.1.dist-info/top_level.txt
easy_oidc_flow-1.0.1.dist-info/RECORD
