Metadata-Version: 2.2
Name: easy_oidc_flow
Version: 1.0.1
Summary: a Flask wrapper which handles OIDC authentication, authorization, and the OAuth flow for a given Identity Provider.
Requires-Python: >=3.12
Requires-Dist: blinker>=1.9.0
Requires-Dist: certifi>=2025.1.31
Requires-Dist: cffi>=1.17.1
Requires-Dist: charset-normalizer>=3.4.1
Requires-Dist: click>=8.1.8
Requires-Dist: colorama>=0.4.6
Requires-Dist: cryptography>=44.0.2
Requires-Dist: flask>=3.1.0
Requires-Dist: idna>=3.10
Requires-Dist: itsdangerous>=2.2.0
Requires-Dist: jinja2>=3.1.6
Requires-Dist: markupsafe>=3.0.2
Requires-Dist: oauthlib>=3.2.2
Requires-Dist: pycparser>=2.22
Requires-Dist: pyjwt>=2.10.1
Requires-Dist: requests>=2.32.3
Requires-Dist: requests-oauthlib>=2.0.0
Requires-Dist: urllib3>=2.3.0
Requires-Dist: werkzeug>=3.1.3
